chunkingdatamodel/__init__.py
chunkingdatamodel/chunking_model.py
chunkingdatamodel/document.py
chunkingmethods/__init__.py
chunkingmethods/adaptive_chunking.py
chunkingmethods/base_chunking.py
chunkingmethods/fixed_length_chunking.py
chunkingmethods/keywords_chunking.py
chunkingmethods/paragraph_chunking.py
chunkingmethods/sentence_chunking.py
chunkingmethods/sliding_window_chunking.py
data_extraction/__init__.py
data_extraction/document_parser.py
data_extraction/excel_parser.py
data_extraction/image_parser.py
chunking4rag-0.0.5.dist-info/LICENSE
chunking4rag-0.0.5.dist-info/METADATA
chunking4rag-0.0.5.dist-info/WHEEL
chunking4rag-0.0.5.dist-info/top_level.txt
chunking4rag-0.0.5.dist-info/RECORD
