Metadata-Version: 2.2
Name: chunking4rag
Version: 0.0.5
Summary: A small library to chunk large files into smaller arrays that can be used for generating RAG embeddings
Home-page: https://github.com/harpreetset1/chunking4rag
Author: Harpreet Sethi
Author-email: Harpreet Sethi <harpreetset@gmail.com>
Classifier: Development Status :: 3 - Alpha
Classifier: Programming Language :: Python :: 3
Classifier: License :: OSI Approved :: MIT License
Classifier: Operating System :: OS Independent
Requires-Python: >=3.12
License-File: LICENSE
Requires-Dist: fastexcel>=0.13.0
Requires-Dist: gensim>=4.3.3
Requires-Dist: html2text>=2024.2.26
Requires-Dist: nltk>=3.9.1
Requires-Dist: pillow>=11.1.0
Requires-Dist: polars>=1.23.0
Requires-Dist: pydantic>=2.10.6
Requires-Dist: pypdf>=5.3.0
Requires-Dist: pytesseract>=0.3.13
Provides-Extra: test
Requires-Dist: pytest; extra == "test"
Requires-Dist: pytest-cov; extra == "test"
Provides-Extra: formatting
Requires-Dist: black; extra == "formatting"
Requires-Dist: flake8; extra == "formatting"
Requires-Dist: isort; extra == "formatting"
Provides-Extra: type-checking
Requires-Dist: mypy; extra == "type-checking"
Provides-Extra: docs
Requires-Dist: pydocstyle; extra == "docs"
Provides-Extra: publishing
Requires-Dist: twine; extra == "publishing"
Requires-Dist: wheel; extra == "publishing"
